{
	"configurations" : 
	[
		{
			"directories" : 
			[
				{
					"build" : ".",
					"jsonFile" : "directory-.-d0094a50bb2071803777.json",
					"minimumCMakeVersion" : 
					{
						"string" : "3.28"
					},
					"projectIndex" : 0,
					"source" : ".",
					"targetIndexes" : 
					[
						0
					]
				}
			],
			"name" : "",
			"projects" : 
			[
				{
					"directoryIndexes" : 
					[
						0
					],
					"name" : "search_analysis_via_wikipedia_graphs",
					"targetIndexes" : 
					[
						0
					]
				}
			],
			"targets" : 
			[
				{
					"directoryIndex" : 0,
					"id" : "search_analysis_via_wikipedia_graphs::@6890427a1f51a3e7e1df",
					"jsonFile" : "target-search_analysis_via_wikipedia_graphs-907a6492e9145b3ca85f.json",
					"name" : "search_analysis_via_wikipedia_graphs",
					"projectIndex" : 0
				}
			]
		}
	],
	"kind" : "codemodel",
	"paths" : 
	{
		"build" : "C:/Users/kev77/CLionProjects/search-analysis-via-wikipedia-graphs/cmake-build-default",
		"source" : "C:/Users/kev77/CLionProjects/search-analysis-via-wikipedia-graphs"
	},
	"version" : 
	{
		"major" : 2,
		"minor" : 6
	}
}
